{"error":"","result":{"total":4,"rows":[
	{"dlmc":"黄科路","ydpsb":"方屏","rwlx":"动态发布","xxlx":"宣传文字","rwmc":"抓拍","fbzt":"启用",
	"fbfs":"离线","fbz":"张三","fbsj":"2016/05/11","error":"记录失败！"	},{"dlmc":"黄科路","ydpsb":"方屏","rwlx":"日常发布","xxlx":"违法警示","rwmc":"抓拍","fbzt":"启用",
	"fbfs":"离线","fbz":"张三","fbsj":"2016/05/11","error":"记录失败！"	},{"dlmc":"黄科路","ydpsb":"方屏","rwlx":"日常发布","xxlx":"交通路况","rwmc":"抓拍","fbzt":"启用",
	"fbfs":"离线","fbz":"张三","fbsj":"2016/05/11","error":"记录失败！"	},{"dlmc":"黄科路","ydpsb":"方屏","rwlx":"紧急发布","xxlx":"安全提示","rwmc":"抓拍","fbzt":"启用",
	"fbfs":"离线","fbz":"张三","fbsj":"2016/05/11","error":"记录失败！"	}
	]
}
}
